sortlabs.py
sortlabs-1.0.dist-info/METADATA
sortlabs-1.0.dist-info/WHEEL
sortlabs-1.0.dist-info/licenses/LICENSE
sortlabs-1.0.dist-info/RECORD
