Metadata-Version: 2.3
Name: sortlabs
Version: 1.0
Summary: A collection of utility functions for working with arrays
Project-URL: Homepage, https://pypi.org/project/sortlabs/
Author-email: Andrea Peretti <andrea.per@gmail.com>
License-File: LICENSE
Classifier: License :: OSI Approved :: MIT License
Classifier: Operating System :: OS Independent
Classifier: Programming Language :: Python :: 3
Requires-Python: >=3.8
